pyncbitk/CMakeLists.txt
pyncbitk/__init__.py
pyncbitk/_utils.py
pyncbitk/objmgr.abi3.so
pyncbitk/objmgr.pxd
pyncbitk/objmgr.pyi
pyncbitk/objmgr.pyx
pyncbitk/objtools.abi3.so
pyncbitk/objtools.pxd
pyncbitk/objtools.pyi
pyncbitk/objtools.pyx
pyncbitk/py.typed
pyncbitk/serial.abi3.so
pyncbitk/serial.pxd
pyncbitk/serial.pyi
pyncbitk/serial.pyx
pyncbitk/algo/CMakeLists.txt
pyncbitk/algo/__init__.pxd
pyncbitk/algo/__init__.py
pyncbitk/algo/blast.abi3.so
pyncbitk/algo/blast.pxd
pyncbitk/algo/blast.pyi
pyncbitk/algo/blast.pyx
pyncbitk/objects/CMakeLists.txt
pyncbitk/objects/__init__.pxd
pyncbitk/objects/__init__.py
pyncbitk/objects/general.abi3.so
pyncbitk/objects/general.pxd
pyncbitk/objects/general.pyi
pyncbitk/objects/general.pyx
pyncbitk/objects/seq.abi3.so
pyncbitk/objects/seq.pxd
pyncbitk/objects/seq.pyi
pyncbitk/objects/seq.pyx
pyncbitk/objects/seqalign.abi3.so
pyncbitk/objects/seqalign.pxd
pyncbitk/objects/seqalign.pyx
pyncbitk/objects/seqdata.abi3.so
pyncbitk/objects/seqdata.pxd
pyncbitk/objects/seqdata.pyi
pyncbitk/objects/seqdata.pyx
pyncbitk/objects/seqdesc.abi3.so
pyncbitk/objects/seqdesc.pxd
pyncbitk/objects/seqdesc.pyi
pyncbitk/objects/seqdesc.pyx
pyncbitk/objects/seqid.abi3.so
pyncbitk/objects/seqid.pxd
pyncbitk/objects/seqid.pyi
pyncbitk/objects/seqid.pyx
pyncbitk/objects/seqinst.abi3.so
pyncbitk/objects/seqinst.pxd
pyncbitk/objects/seqinst.pyi
pyncbitk/objects/seqinst.pyx
pyncbitk/objects/seqloc.abi3.so
pyncbitk/objects/seqloc.pxd
pyncbitk/objects/seqloc.pyi
pyncbitk/objects/seqloc.pyx
pyncbitk/objects/seqset.abi3.so
pyncbitk/objects/seqset.pxd
pyncbitk/objects/seqset.pyi
pyncbitk/objects/seqset.pyx
pyncbitk/objects/taxon.abi3.so
pyncbitk/objects/taxon.pyx
pyncbitk/toolkit/__init__.pxd
pyncbitk/toolkit/algo/__init__.pxd
pyncbitk/toolkit/algo/blast/__init__.pxd
pyncbitk/toolkit/algo/blast/api/__init__.pxd
pyncbitk/toolkit/algo/blast/api/bl2seq.pxd
pyncbitk-0.1.0a5.dist-info/METADATA
pyncbitk-0.1.0a5.dist-info/WHEEL
pyncbitk-0.1.0a5.dist-info/RECORD
pyncbitk-0.1.0a5.dist-info/licenses/COPYING
