Metadata-Version: 2.2
Name: pyncbitk
Version: 0.1.0a5
Summary: Cython bindings and Python interface to the NCBI C++ Toolkit.
Keywords: bioinformatics,blast,sequence,alignment,ncbi
Author-Email: Martin Larralde <martin.larralde@embl.de>
License: MIT License
Classifier: Development Status :: 3 - Alpha
Classifier: Intended Audience :: Developers
Classifier: Intended Audience :: Science/Research
Classifier: License :: OSI Approved :: MIT License
Classifier: Operating System :: OS Independent
Classifier: Programming Language :: C++
Classifier: Programming Language :: Cython
Classifier: Programming Language :: Python :: 3.7
Classifier: Programming Language :: Python :: 3.8
Classifier: Programming Language :: Python :: 3.9
Classifier: Programming Language :: Python :: 3.10
Classifier: Programming Language :: Python :: 3.11
Classifier: Programming Language :: Python :: 3.12
Classifier: Programming Language :: Python :: 3.13
Classifier: Programming Language :: Python :: 3.14
Classifier: Programming Language :: Python :: Implementation :: CPython
Classifier: Programming Language :: Python :: Implementation :: PyPy
Classifier: Topic :: Scientific/Engineering :: Bio-Informatics
Classifier: Topic :: Scientific/Engineering :: Medical Science Apps.
Classifier: Typing :: Typed
Project-URL: Documentation, https://pyncbitk.readthedocs.io/en/stable/
Project-URL: Bug Tracker, https://github.com/althonos/pyncbitk/issues
Project-URL: Changelog, https://github.com/althonos/pyncbitk/blob/master/CHANGELOG.md
Project-URL: Coverage, https://codecov.io/gh/althonos/pyncbitk/
Project-URL: Builds, https://github.com/althonos/pyncbitk/actions
Project-URL: PyPI, https://pypi.org/project/pyncbitk
Requires-Python: >=3.7
Requires-Dist: pyncbitk-runtime~=29.6
